segment/analytics/__init__.py
segment/analytics/client.py
segment/analytics/consumer.py
segment/analytics/oauth_manager.py
segment/analytics/request.py
segment/analytics/utils.py
segment/analytics/version.py
segment/analytics/test/__init__.py
segment/analytics/test/client.py
segment/analytics/test/consumer.py
segment/analytics/test/module.py
segment/analytics/test/oauth.py
segment/analytics/test/request.py
segment/analytics/test/test_client.py
segment/analytics/test/test_consumer.py
segment/analytics/test/test_init.py
segment/analytics/test/test_module.py
segment/analytics/test/test_oauth.py
segment/analytics/test/test_request.py
segment/analytics/test/test_utils.py
segment/analytics/test/utils.py
segment_analytics_python-2.3.4.dist-info/LICENSE
segment_analytics_python-2.3.4.dist-info/METADATA
segment_analytics_python-2.3.4.dist-info/WHEEL
segment_analytics_python-2.3.4.dist-info/top_level.txt
segment_analytics_python-2.3.4.dist-info/RECORD
