Metadata-Version: 2.2
Name: segment-analytics-python
Version: 2.3.4
Summary: The hassle-free way to integrate analytics into any python application.
Home-page: https://github.com/segmentio/analytics-python
Author: Segment
Author-email: friends@segment.com
Maintainer: Segment
Maintainer-email: friends@segment.com
License: MIT License
Classifier: Development Status :: 5 - Production/Stable
Classifier: Intended Audience :: Developers
Classifier: License :: OSI Approved :: MIT License
Classifier: Operating System :: OS Independent
Classifier: Programming Language :: Python
Classifier: Programming Language :: Python :: 3.9
Classifier: Programming Language :: Python :: 3.10
Classifier: Programming Language :: Python :: 3.11
Requires-Python: >=3.9.0
License-File: LICENSE
Requires-Dist: requests~=2.7
Requires-Dist: backoff~=2.1
Requires-Dist: python-dateutil~=2.2
Requires-Dist: PyJWT~=2.10.1
Provides-Extra: test
Requires-Dist: mock==2.0.0; extra == "test"
Requires-Dist: pylint==3.3.1; extra == "test"
Requires-Dist: flake8==3.7.9; extra == "test"
Dynamic: author
Dynamic: author-email
Dynamic: classifier
Dynamic: description
Dynamic: home-page
Dynamic: license
Dynamic: maintainer
Dynamic: maintainer-email
Dynamic: provides-extra
Dynamic: requires-dist
Dynamic: requires-python
Dynamic: summary
